abstract_videos/__init__.py
abstract_videos/audio_utils.py
abstract_videos/compatability_utils.py
abstract_videos/file_utils.py
abstract_videos/pipeline.py
abstract_videos/routes.py
abstract_videos/thumbnail_utils.py
abstract_videos/video_calls.py
abstract_videos/old/__init__.py
abstract_videos/old/audio_utils.py
abstract_videos/old/audio_utils_clean.py
abstract_videos/old/audio_utils_old.py
abstract_videos/old/download_pdf.py
abstract_videos/old/functions.py
abstract_videos/old/linetest.py
abstract_videos/old/macros.py
abstract_videos/old/ocr_utils.py
abstract_videos/old/pdf_utils.py
abstract_videos/old/repo_utils.py
abstract_videos/old/routes.py
abstract_videos/old/seo_utils.py
abstract_videos/old/text_utils.py
abstract_videos/old/transcribe_audio.py
abstract_videos/old/transcribe_utils.py
abstract_videos/old/variable_utils.py
abstract_videos/old/video_utils.py
abstract_videos/seo_utils/__init__.py
abstract_videos/seo_utils/routes.py
abstract_videos/seo_utils/seo_manager.py
abstract_videos/seo_utils/seo_services.py
abstract_videos/text_tools/__init__.py
abstract_videos/text_tools/endpoint.py
abstract_videos/text_tools/routes.py
abstract_videos/text_tools/text_manager.py
abstract_videos/text_tools/generator_utils/__init__.py
abstract_videos/text_tools/generator_utils/generator_services.py
abstract_videos/text_tools/generator_utils/routes.py
abstract_videos/text_tools/keybert_utils/__init__.py
abstract_videos/text_tools/keybert_utils/keybert_call_schema.py
abstract_videos/text_tools/keybert_utils/keybert_calls.py
abstract_videos/text_tools/keybert_utils/keybert_get_data.py
abstract_videos/text_tools/keybert_utils/keybert_manager.py
abstract_videos/text_tools/keybert_utils/keybert_services.py
abstract_videos/text_tools/keybert_utils/routes.py
abstract_videos/text_tools/summarizer_utils/__init__.py
abstract_videos/text_tools/summarizer_utils/routes.py
abstract_videos/text_tools/summarizer_utils/summarizer_call_schema.py
abstract_videos-0.0.0.257.dist-info/METADATA
abstract_videos-0.0.0.257.dist-info/WHEEL
abstract_videos-0.0.0.257.dist-info/top_level.txt
abstract_videos-0.0.0.257.dist-info/RECORD
